{
    "models": [
        {
            "orientability": "full",
            "noun": "chair",
            "nounIndex": 0,
            "verbs": [],
            "adjectives": []
        },
        {
            "orientability": "vertical",
            "noun": "table",
            "nounIndex": 0,
            "verbs": [],
            "adjectives": []
        },
        {
            "orientability": "full",
            "noun": "toaster",
            "nounIndex": 0,
            "verbs": [],
            "adjectives": []
        },
        {
            "orientability": "full",
            "noun": "cat",
            "nounIndex": 0,
            "verbs": [],
            "adjectives": [
                "orange"
            ]
        },
        {
            "orientability": "none",
            "noun": "baseball",
            "nounIndex": 0,
            "verbs": [],
            "adjectives": []
        }
    ]
}
